ob7py/__init__.py
ob7py/dumbserver.py
ob7py/iotest.py
ob7py/ob7py.py
ob7py/testprog.py
ob7py-0.0.2.dist-info/LICENSE.txt
ob7py-0.0.2.dist-info/METADATA
ob7py-0.0.2.dist-info/WHEEL
ob7py-0.0.2.dist-info/top_level.txt
ob7py-0.0.2.dist-info/RECORD
