Metadata-Version: 2.1
Name: ob7py
Version: 0.0.2
Summary: Python for Productive Robotics ob7 Platform
Author-email: Michael Dillio <mdillio@praxismechatronics.com>
License: MIT License
Keywords: robotics,automation,mechatronics,ob7
Classifier: Development Status :: 3 - Alpha
Classifier: Intended Audience :: Developers
Classifier: Topic :: Software Development :: Build Tools
Classifier: License :: OSI Approved :: MIT License
Classifier: Programming Language :: Python :: 3
Classifier: Programming Language :: Python :: 3.7
Classifier: Programming Language :: Python :: 3.8
Classifier: Programming Language :: Python :: 3.9
Classifier: Programming Language :: Python :: 3.10
Classifier: Programming Language :: Python :: 3.11
Requires-Python: >=3.7
License-File: LICENSE.txt
Requires-Dist: pyModbusTCP ==0.2.1
Requires-Dist: pymodbus ==3.6.2
